{"description":"TestCase 6:- Sign Up with all valid data and  empty DOB|Sign Up","passed":true,"pending":false,"os":"Linux","sessionId":"6b9f112bc60947e58358f3c980e492a3","instanceId":30179,"browser":{"name":"chrome","version":"73.0.3683.86"},"message":"Passed.","trace":"","browserLogs":[{"level":"WARNING","message":"https://alpha.woovly.com/js/Precommon.js?v=4094 43 Synchronous XMLHttpRequest on the main thread is deprecated because of its detrimental effects to the end user's experience. For more help, check https://xhr.spec.whatwg.org/.","timestamp":1554200894775,"type":""}],"screenShotFile":"00ec0076-0082-0047-00af-005800b100fa.png","timestamp":1554200894470,"duration":6074}
